geostrokit/__init__.py
geostrokit/energy.py
geostrokit/fftlib.py
geostrokit/grid.py
geostrokit/inout.py
geostrokit/mgd2d.py
geostrokit/omega.py
geostrokit/operators.py
geostrokit/pv.py
geostrokit/stability.py
geostrokit/variability.py
geostrokit-0.7.1.dist-info/WHEEL
geostrokit-0.7.1.dist-info/METADATA
geostrokit-0.7.1.dist-info/RECORD
